accession/__init__.py
accession/__main__.py
accession/accession.py
accession/accession_steps.py
accession/analysis.py
accession/backends.py
accession/caper_helper.py
accession/cloud_tasks.py
accession/encode_models.py
accession/file.py
accession/helpers.py
accession/logger_factory.py
accession/metadata.py
accession/metadata_preprocessors.py
accession/preflight.py
accession/task.py
accession/database/__init__.py
accession/database/connection.py
accession/database/models.py
accession/database/query.py
accession/subcommands/__init__.py
accession/subcommands/info.py
accession_steps/__init__.py
accession_steps/atac_steps.json
accession_steps/bulk_rna_no_kallisto_steps.json
accession_steps/bulk_rna_pbam_steps.json
accession_steps/bulk_rna_steps.json
accession_steps/chip_map_only_steps.json
accession_steps/control_chip_pbam_steps.json
accession_steps/control_chip_steps.json
accession_steps/diploidify_steps.json
accession_steps/dnase_no_footprints_steps.json
accession_steps/dnase_starch_from_bam_steps.json
accession_steps/dnase_steps.json
accession_steps/genophase_steps.json
accession_steps/hic_intact_low_contact_steps.json
accession_steps/hic_intact_steps.json
accession_steps/hic_low_contact_steps.json
accession_steps/hic_steps.json
accession_steps/histone_chip_pbam_steps.json
accession_steps/histone_chip_peak_call_only_steps.json
accession_steps/histone_chip_steps.json
accession_steps/long_read_rna_no_spikeins_steps.json
accession_steps/long_read_rna_one_spikein_steps.json
accession_steps/long_read_rna_two_or_more_spikeins_steps.json
accession_steps/megamap_steps.json
accession_steps/mint_chip_peak_call_only_steps.json
accession_steps/mint_chip_steps.json
accession_steps/mirna_steps.json
accession_steps/segway_steps.json
accession_steps/tf_chip_bwa_control_fastqs_steps.json
accession_steps/tf_chip_pbam_steps.json
accession_steps/tf_chip_peak_call_only_steps.json
accession_steps/tf_chip_steps.json
accession_steps/wgbs_steps.json
tests/__init__.py
tests/conftest.py
accession-4.8.4.dist-info/LICENSE
accession-4.8.4.dist-info/METADATA
accession-4.8.4.dist-info/WHEEL
accession-4.8.4.dist-info/entry_points.txt
accession-4.8.4.dist-info/top_level.txt
accession-4.8.4.dist-info/RECORD
