Metadata-Version: 2.1
Name: accession
Version: 4.8.4
Summary: Tool to submit genomics pipeline outputs to the ENCODE Portal
Home-page: https://github.com/ENCODE-DCC/accession
Author: Paul Sud
Author-email: encode-help@lists.stanford.edu
License: MIT
Project-URL: Documentation, https://accession.readthedocs.io/en/latest/
Project-URL: Source Code, https://github.com/ENCODE-DCC/accession
Project-URL: Issue Tracker, https://github.com/ENCODE-DCC/accession/issues
Classifier: License :: OSI Approved :: MIT License
Classifier: Natural Language :: English
Classifier: Operating System :: OS Independent
Classifier: Programming Language :: Python
Classifier: Programming Language :: Python :: 3
Classifier: Programming Language :: Python :: 3.6
Classifier: Programming Language :: Python :: 3.7
Classifier: Programming Language :: Python :: 3.8
Requires-Python: >=3.6
License-File: LICENSE
Requires-Dist: SQLAlchemy (==1.3.17)
Requires-Dist: attrs
Requires-Dist: protobuf (==3.20.1)
Requires-Dist: boto3 (==1.17.108)
Requires-Dist: caper (==1.5.1)
Requires-Dist: encode-utils (==2.10.0)
Requires-Dist: flatdict (==4.0.1)
Requires-Dist: google-api-core (==1.21.0)
Requires-Dist: google-auth (==1.18.0)
Requires-Dist: google-cloud-storage (==1.28.1)
Requires-Dist: google-cloud-tasks (==1.5.0)
Requires-Dist: miniwdl (==0.8.2)
Requires-Dist: qc-utils (==20.9.1)
Requires-Dist: typing-extensions (==3.7.4.2)
Provides-Extra: dev
Requires-Dist: sphinx ; extra == 'dev'
Requires-Dist: pytest ; extra == 'dev'
Requires-Dist: pytest-cov ; extra == 'dev'
Requires-Dist: pytest-mock (==3.6.1) ; extra == 'dev'
Requires-Dist: docker ; extra == 'dev'
Requires-Dist: requests ; extra == 'dev'
Requires-Dist: pre-commit ; extra == 'dev'
Requires-Dist: sqlalchemy-stubs (==0.3) ; extra == 'dev'
Requires-Dist: boto3-stubs[s3] ; extra == 'dev'
Provides-Extra: docs
Requires-Dist: sphinx ; extra == 'docs'
Provides-Extra: tests
Requires-Dist: pytest ; extra == 'tests'
Requires-Dist: pytest-cov ; extra == 'tests'
Requires-Dist: pytest-mock (==3.6.1) ; extra == 'tests'
Requires-Dist: docker ; extra == 'tests'
Requires-Dist: requests ; extra == 'tests'
